<annotation>
  <folder>12--Group</folder>
  <filename>12_Group_Large_Group_12_Group_Large_Group_12_493.jpg</filename>
  <path>E:/DB_FaceLandmark/WFLW/WFLW_images/12--Group/12_Group_Large_Group_12_Group_Large_Group_12_493.jpg</path>
  <size>
    <height>701</height>
    <width>1024</width>
    <depth>3</depth>
  </size>
  <object>
    <bbox>
      <xmin>743</xmin>
      <ymin>262</ymin>
      <xmax>805</xmax>
      <ymax>335</ymax>
    </bbox>
    <landmarks>747.868347 294.188110 749.099539 296.985510 750.206115 299.833929 751.042063 302.772071 751.537226 305.786566 751.890070 308.822384 752.622101 311.782374 754.184909 314.396263 756.298984 316.599074 758.585969 318.626671 760.784225 320.748720 762.667813 323.150015 764.085327 325.854706 765.262691 328.675142 766.661784 331.383848 769.298755 332.655033 772.284131 332.061259 776.325729 330.570291 780.407010 329.190507 784.353197 327.468230 788.065208 325.285422 791.548712 322.752377 794.824875 319.955615 797.876631 316.916412 800.565720 313.554532 802.665961 309.800122 803.978806 305.703716 804.597553 301.443537 804.700502 297.138169 804.424828 292.839621 803.864213 288.568382 803.112276 284.326276 802.265015 280.101990 746.744019 289.773987 748.059021 287.511993 749.760986 287.515991 751.447998 287.459015 753.288025 287.497009 753.664978 289.437988 751.915955 289.510010 750.166016 289.582001 748.492981 289.702026 758.862976 285.423004 761.616028 284.082001 764.239990 283.076996 767.473022 282.951019 771.448975 286.528961 768.179993 286.050995 764.924927 286.079987 762.137024 286.816986 759.437012 287.942017 757.776001 292.785004 756.959314 297.814472 756.383228 302.875392 755.600000 307.900000 758.507996 310.595978 759.413272 310.038875 760.332749 309.505656 763.266932 308.329741 766.408020 307.908997 749.176941 296.809082 749.384060 295.837255 749.942016 295.037331 752.344026 294.711356 754.697021 295.446014 753.157817 296.920107 751.240998 297.797242 750.091433 297.573403 763.260986 291.727997 764.023121 290.018440 765.690025 289.232654 768.229140 289.042426 770.768982 289.241669 769.317712 290.338887 767.721835 291.207230 765.527841 291.755035 760.408936 319.235992 760.597494 316.702840 763.049857 316.290592 764.183247 316.293786 764.907989 316.176189 771.690023 314.884550 778.421021 313.109985 774.747007 316.299713 770.406804 318.584406 765.901951 320.521572 763.926312 321.088748 761.976239 320.571970 760.455444 319.222687 762.419037 318.825504 764.378458 318.408311 770.985378 316.574139 777.265991 313.824005 771.169149 316.508870 764.759060 318.323052 762.610029 318.786088 750.700000 296.500000 767.500000 290.900000</landmarks>
  </object>
</annotation>
