<annotation>
  <folder>7--Cheering</folder>
  <filename>7_Cheering_Cheering_7_460.jpg</filename>
  <path>E:/DB_FaceLandmark/WFLW/WFLW_images/7--Cheering/7_Cheering_Cheering_7_460.jpg</path>
  <size>
    <height>714</height>
    <width>1024</width>
    <depth>3</depth>
  </size>
  <object>
    <bbox>
      <xmin>322</xmin>
      <ymin>358</ymin>
      <xmax>438</xmax>
      <ymax>500</ymax>
    </bbox>
    <landmarks>327.030426 419.530548 329.548896 426.840467 332.122713 434.131043 334.806200 441.381886 337.650047 448.571275 340.733734 455.660460 344.353572 462.487795 348.850635 468.768190 354.217756 474.324773 360.285318 479.107248 366.883247 483.131935 373.512888 487.103711 379.498932 491.983909 385.489278 496.851163 392.608143 499.757845 400.298772 500.236703 407.625527 497.973020 413.336746 493.538612 418.199939 488.162410 422.430022 482.279473 425.828668 475.877761 428.658656 469.201619 431.357669 462.470540 434.182241 455.791143 436.829753 449.041425 438.506683 441.999649 438.539501 434.763046 437.361953 427.609662 435.951685 420.495988 434.578300 413.375105 433.228058 406.249790 431.895279 399.121187 430.571014 391.990997 337.072998 410.841003 340.626007 400.938995 348.174988 396.296021 356.712006 396.787994 366.030975 396.467987 367.199005 401.705994 357.750000 401.463013 349.125000 400.010010 341.338959 404.091003 388.152985 391.040985 394.790955 384.899994 400.722992 380.528992 407.506012 377.114075 416.184998 378.519989 408.302002 380.059967 401.952972 384.346008 396.433960 390.974976 389.447968 395.828003 381.640015 406.433990 384.447255 416.678652 386.934674 426.988434 391.351553 436.255901 380.140015 441.119995 385.825157 441.139515 391.474107 441.012067 396.399315 438.413805 401.593903 436.407043 346.122864 416.669067 350.596773 413.584953 355.597182 411.489055 361.066605 410.963135 366.397003 412.365997 361.545089 414.450068 356.370624 415.483213 351.231852 415.949211 393.815002 404.990997 398.273937 400.114622 403.443279 396.068218 408.627955 395.006514 413.857178 396.031738 410.005993 398.839203 405.618923 400.681772 399.582561 402.473536 366.717499 458.817993 377.574616 451.585564 390.285039 449.003722 393.440483 448.355538 395.847199 447.527266 407.534489 443.696208 419.810944 444.113007 417.203202 456.359879 412.329978 467.788167 401.681692 474.023997 387.947562 475.762355 375.741700 469.426331 367.458496 458.730499 380.301050 452.470432 394.521769 450.461076 406.457847 446.123435 419.082855 444.912231 413.476267 460.058308 400.143534 468.841840 382.166098 469.260099 356.068323 413.503106 403.571429 399.391304</landmarks>
  </object>
</annotation>
