<annotation>
  <folder>20--Family_Group</folder>
  <filename>20_Family_Group_Family_Group_20_491.jpg</filename>
  <path>E:/DB_FaceLandmark/WFLW/WFLW_images/20--Family_Group/20_Family_Group_Family_Group_20_491.jpg</path>
  <size>
    <height>768</height>
    <width>1024</width>
    <depth>3</depth>
  </size>
  <object>
    <bbox>
      <xmin>460</xmin>
      <ymin>404</ymin>
      <xmax>534</xmax>
      <ymax>506</ymax>
    </bbox>
    <landmarks>461.941010 442.852997 462.338658 448.190422 462.658024 453.533004 462.824999 458.882368 462.764363 464.233631 462.471635 469.577712 462.375537 474.926238 463.408924 480.155008 465.988771 484.824858 469.517236 488.842265 473.467483 492.451978 477.544839 495.919165 481.613056 499.397069 485.811511 502.714317 490.385226 505.480473 495.469273 507.097113 500.804086 507.243631 505.483839 506.375273 509.977379 504.800376 514.230351 502.657233 518.197246 500.021690 521.810412 496.919549 524.977572 493.364129 527.591680 489.385286 529.554655 485.048370 530.896888 480.478833 531.784053 475.797976 532.387915 471.071354 532.872968 466.330713 533.363524 461.590630 533.884248 456.853765 534.423946 452.119020 534.973755 447.385437 472.578979 433.684967 478.740967 430.997955 485.353973 431.115967 491.692963 432.127014 496.846954 433.936951 496.388000 436.651001 491.379974 435.222992 484.694977 433.992981 478.664001 433.566010 510.103973 433.707001 515.021973 432.804962 520.401978 433.505981 525.548950 434.962006 530.029968 438.373962 525.036987 436.933990 520.135925 436.125946 514.678955 436.195007 509.653015 436.619965 502.506012 440.645996 502.019953 447.623531 501.407112 454.590174 501.266258 461.570552 494.171997 462.683014 497.600734 464.144031 500.874648 465.865119 504.369078 464.156706 508.202911 464.289001 478.117004 440.886993 481.601905 437.742088 486.312921 437.577731 489.500458 438.893510 491.954315 441.348999 489.297027 443.005964 486.248226 443.634095 482.041875 442.717242 511.532013 443.756012 514.307760 440.839082 518.267893 440.251949 522.043203 441.496991 524.871216 444.323730 521.603456 446.170207 517.846123 446.144366 514.544988 445.337468 480.428497 472.366516 489.589660 472.338772 498.696917 473.205470 500.837382 473.171438 502.642900 472.972844 509.489804 473.507901 515.984253 475.886505 512.583328 481.458405 506.616024 483.917678 500.075792 483.677671 492.293878 481.729558 484.797580 478.944980 482.565002 474.153503 491.785224 474.254553 500.887406 475.777140 507.869566 475.455508 514.783630 476.462372 508.038677 479.383751 500.719082 479.769768 491.344405 477.933390 485.496933 441.671166 517.786503 444.674847</landmarks>
  </object>
</annotation>
