<annotation>
  <folder>12--Group</folder>
  <filename>12_Group_Group_12_Group_Group_12_728.jpg</filename>
  <path>E:/DB_FaceLandmark/WFLW/WFLW_images/12--Group/12_Group_Group_12_Group_Group_12_728.jpg</path>
  <size>
    <height>740</height>
    <width>1024</width>
    <depth>3</depth>
  </size>
  <object>
    <bbox>
      <xmin>820</xmin>
      <ymin>118</ymin>
      <xmax>916</xmax>
      <ymax>240</ymax>
    </bbox>
    <landmarks>819.861023 175.371994 820.156339 180.494950 820.550883 185.611057 821.144541 190.707579 822.024052 195.762225 823.265049 200.739981 824.927106 205.592956 827.034164 210.269796 829.581460 214.721947 832.567431 218.892450 835.944699 222.753756 839.567068 226.387801 843.268030 229.942370 846.952667 233.513841 850.660054 237.061455 854.793363 240.073525 859.701095 241.477927 866.299560 241.054659 872.671598 239.218248 878.750980 236.562817 884.487747 233.229906 889.865374 229.342156 894.930431 225.053439 899.781314 220.522818 904.524495 215.879081 909.098699 211.080378 911.900920 205.120164 912.769545 198.542390 913.503910 191.945355 913.947181 185.323170 913.935269 178.686657 913.549699 172.060353 912.982849 165.446686 821.153076 166.643036 825.177063 156.572006 831.108032 155.688019 837.238037 154.879013 843.058044 156.682007 843.371033 161.485016 837.697083 160.375000 831.651062 161.080017 825.833984 163.099030 857.322083 152.969025 864.786072 148.479019 872.830078 146.459015 881.778076 146.877029 890.324036 152.942032 882.392090 151.873001 873.542053 152.435013 865.335083 153.921021 857.921997 157.676025 849.622009 168.595993 850.315852 176.991809 851.061089 185.382777 851.458683 193.789222 844.310974 198.548996 848.879174 200.172418 853.665280 200.807611 860.113028 199.339179 866.171814 196.621063 825.255981 173.613007 827.373410 170.766627 830.435283 169.050438 836.303385 168.964203 841.332520 171.986053 836.627981 174.038914 831.556295 174.710648 828.377361 174.335271 865.390991 168.276993 869.138114 163.401525 874.935450 161.428651 879.096563 161.769385 883.122070 162.918350 879.781245 166.029644 875.673152 167.983152 870.553575 168.624794 838.869507 209.524994 845.137578 208.590974 851.307003 207.145303 856.084792 205.847249 861.718549 204.651982 871.334960 204.039646 880.976135 203.775711 875.597476 212.686280 867.564891 219.216756 857.585114 222.054226 849.765861 220.956796 843.573469 215.984318 839.736511 209.813004 848.301868 208.335662 856.917917 207.196666 868.399090 206.234292 879.760193 204.349365 870.010796 212.452151 857.944353 216.262475 847.961238 215.609649 835.851497 171.679042 876.603593 163.008383</landmarks>
  </object>
</annotation>
