<annotation>
  <folder>8--Election_Campain</folder>
  <filename>8_Election_Campain_Election_Campaign_8_416.jpg</filename>
  <path>E:/DB_FaceLandmark/WFLW/WFLW_images/8--Election_Campain/8_Election_Campain_Election_Campaign_8_416.jpg</path>
  <size>
    <height>1244</height>
    <width>1024</width>
    <depth>3</depth>
  </size>
  <object>
    <bbox>
      <xmin>251</xmin>
      <ymin>265</ymin>
      <xmax>640</xmax>
      <ymax>817</ymax>
    </bbox>
    <landmarks>262.423187 399.861450 258.015601 428.127301 251.833276 456.051132 243.793199 483.505209 239.373349 511.713705 240.888317 540.243725 245.004380 568.554622 248.589025 596.936485 252.411190 625.283202 260.999297 652.480003 273.889480 678.018109 284.287183 704.633544 293.291888 731.759344 308.744068 755.708361 330.263691 774.455890 355.068174 788.640154 381.846909 798.626147 414.095133 805.037773 446.946523 806.093285 479.270685 800.245308 509.855301 788.173901 538.642170 772.248085 565.578826 753.356650 590.488320 731.859760 613.253535 708.103155 633.456902 682.139614 650.249334 653.860033 662.740534 623.439048 671.543056 591.733222 678.499161 559.562613 684.652122 527.227707 690.190148 494.781697 695.336975 462.270996 278.081970 395.449982 306.161987 372.148010 327.184967 383.418976 349.681976 394.884979 370.055969 411.071991 367.891968 431.288971 346.792969 413.006989 324.295959 401.540985 302.561005 395.675995 439.998962 399.071014 481.270966 394.203979 514.807983 397.410980 546.492981 410.074982 576.995911 454.714966 542.519958 435.620972 510.081970 424.071014 477.298004 419.749969 437.845978 420.006989 395.269012 456.696991 383.980476 500.183172 372.655750 543.659836 361.560248 587.193789 337.312988 583.067993 356.494827 598.104664 380.475092 603.223014 409.334096 605.474278 437.343506 598.432190 283.099548 436.244202 295.785830 434.801080 308.538009 434.915089 337.011649 442.322584 359.458008 461.018005 334.433796 461.270506 309.506954 463.031198 291.072498 455.030922 444.683014 469.251007 464.942823 455.502561 489.309362 455.079053 512.235958 462.864574 534.077759 473.416870 513.675957 483.952767 491.191400 487.944864 466.957349 481.246244 321.009491 669.866455 338.760051 657.375962 358.877979 649.403648 369.182880 647.587925 381.659909 647.155230 423.277550 663.031118 462.775574 682.894287 436.974674 701.536048 405.241080 706.419433 373.271466 704.453755 352.313636 698.465358 333.629577 687.578649 329.621521 672.099976 350.318675 663.326669 372.485811 660.388910 415.438804 668.007101 456.530396 682.608398 414.823515 691.305896 372.796820 694.415966 350.006744 685.669223 300.426087 443.693168 484.700621 464.249689</landmarks>
  </object>
</annotation>
