<annotation>
  <folder>2--Demonstration</folder>
  <filename>2_Demonstration_Demonstration_Or_Protest_2_942.jpg</filename>
  <path>E:/DB_FaceLandmark/WFLW/WFLW_images/2--Demonstration/2_Demonstration_Demonstration_Or_Protest_2_942.jpg</path>
  <size>
    <height>1535</height>
    <width>1024</width>
    <depth>3</depth>
  </size>
  <object>
    <bbox>
      <xmin>219</xmin>
      <ymin>99</ymin>
      <xmax>692</xmax>
      <ymax>758</ymax>
    </bbox>
    <landmarks>215.485992 364.431000 213.178206 394.795644 211.533626 425.202188 211.235289 455.649109 212.960761 486.045769 216.594775 516.277134 221.407875 546.345810 226.627296 576.347543 231.587814 606.392873 236.518492 636.442269 243.516800 666.062920 254.984340 694.221568 272.440652 719.083423 294.898728 739.575094 320.848426 755.427040 349.320789 766.089766 379.382998 770.494966 417.391096 766.670947 454.217329 756.265270 490.382747 743.692630 526.215588 730.210436 560.868855 713.972938 592.629094 692.699990 618.403397 664.531610 636.813247 631.035736 649.460936 594.926132 658.128172 557.643172 664.189851 519.842240 668.319494 481.780353 670.799588 443.574268 671.992176 405.305276 672.300535 367.018134 672.156921 328.729584 228.037979 304.127014 258.281006 265.807037 286.437988 259.200958 315.322998 261.151001 342.774994 269.281006 341.346985 299.128998 313.480988 287.763000 285.975006 280.767029 257.898987 285.671997 431.935974 248.772049 473.286987 242.853989 513.698975 240.050034 552.157959 245.048004 589.671997 286.324982 551.216003 264.743988 512.794983 258.958008 472.981995 265.739014 430.755005 278.078979 366.850006 303.015991 361.165365 336.979306 355.274365 370.905604 350.784431 405.011976 325.192993 443.907013 345.470456 447.730809 366.027675 449.176660 400.947790 442.177682 434.040314 428.686340 247.589340 343.755524 263.422078 323.030106 288.271637 315.460390 314.258100 318.198608 334.980011 334.276001 311.826659 339.455643 288.796859 345.117789 268.151718 346.139251 458.385010 320.859009 484.131589 299.008465 517.729762 297.811521 539.908915 308.654876 558.115295 325.515381 534.874055 328.523665 511.467076 328.787004 485.035555 324.106858 310.871002 596.666504 302.635148 528.452993 339.889086 476.657432 363.885866 471.934586 381.346076 470.335389 443.661293 503.366694 469.733337 573.959900 464.973972 626.519187 427.544979 663.818166 377.527527 681.314787 334.690558 673.039052 306.627050 640.246575 321.626526 599.130005 315.788454 531.602391 366.440812 489.342322 434.443341 512.537947 465.090393 579.825562 434.038606 630.744397 379.220686 653.257371 334.499514 643.737697 283.000000 327.059880 501.604790 310.113772</landmarks>
  </object>
</annotation>
