<annotation>
  <folder>24--Soldier_Firing</folder>
  <filename>24_Soldier_Firing_Soldier_Firing_24_536.jpg</filename>
  <path>E:/DB_FaceLandmark/WFLW/WFLW_images/24--Soldier_Firing/24_Soldier_Firing_Soldier_Firing_24_536.jpg</path>
  <size>
    <height>752</height>
    <width>1024</width>
    <depth>3</depth>
  </size>
  <object>
    <bbox>
      <xmin>392</xmin>
      <ymin>338</ymin>
      <xmax>456</xmax>
      <ymax>436</ymax>
    </bbox>
    <landmarks>389.690002 378.735992 389.276831 383.089088 388.909901 387.446285 388.634244 391.810130 388.492715 396.180272 388.539829 400.552193 388.856002 404.912475 389.530895 409.231105 390.659416 413.452979 392.330156 417.489843 394.576246 421.236760 397.343645 424.617482 400.564727 427.569013 404.185309 430.013281 408.146042 431.854437 412.358424 433.007354 416.706229 433.418923 420.494198 433.160542 424.166926 432.217457 427.399527 430.256762 429.810928 427.328683 432.318465 424.478018 435.051302 421.837065 437.485512 418.924430 439.521012 415.716509 441.316133 412.367260 442.930643 408.927119 444.380261 405.414266 445.671329 401.840048 446.814434 398.215747 447.818981 394.550594 448.699037 390.853490 449.500305 387.138397 402.390015 377.199005 408.223999 374.616028 413.937042 375.105988 419.204987 376.339020 424.471985 377.933990 424.157990 380.462036 418.845032 379.554993 413.480988 378.441040 407.991028 377.579041 432.039032 378.934021 436.325989 378.618011 440.519012 378.816040 444.964020 379.069031 448.684998 382.609039 444.947052 381.249023 440.501038 380.996033 436.267029 380.987030 431.934021 381.272034 426.431000 385.192993 426.009071 390.134835 425.303008 394.970847 425.140228 399.048370 416.436005 402.953003 419.582739 403.392164 422.469343 404.757306 426.078127 404.949477 429.579926 405.854980 405.377014 381.300995 408.068638 379.976584 411.032522 379.663892 415.517122 380.988733 419.537262 383.413727 414.828112 384.617787 410.016855 383.805494 407.598251 382.740827 432.450012 384.473999 435.454966 383.297453 438.674112 383.461248 441.921190 384.295275 444.854797 385.920013 441.786525 387.314440 438.422100 387.317512 435.186996 386.425275 405.167480 415.784485 411.416506 413.205472 418.213556 412.937438 422.153517 414.070673 426.151854 414.984121 428.543583 415.897902 430.810944 417.093994 427.811690 419.628619 424.075680 420.756553 420.177228 420.319762 414.939788 419.670566 409.941966 418.048024 405.643005 415.829010 413.601586 414.724269 421.602340 416.029210 425.901200 416.537586 430.179291 417.199677 425.876567 416.534089 421.552863 416.023913 413.576949 414.720802 411.380124 381.351553 438.272050 386.546584</landmarks>
  </object>
</annotation>
