<annotation>
  <folder>53--Raid</folder>
  <filename>53_Raid_policeraid_53_955.jpg</filename>
  <path>E:/DB_FaceLandmark/WFLW/WFLW_images/53--Raid/53_Raid_policeraid_53_955.jpg</path>
  <size>
    <height>577</height>
    <width>1024</width>
    <depth>3</depth>
  </size>
  <object>
    <bbox>
      <xmin>466</xmin>
      <ymin>180</ymin>
      <xmax>564</xmax>
      <ymax>332</ymax>
    </bbox>
    <landmarks>452.576996 241.548996 453.013025 250.721692 453.385042 259.897172 453.626110 269.076930 453.755347 278.259070 454.056764 287.436660 454.905294 296.577562 456.966970 305.512298 460.996296 313.735008 466.804603 320.829970 473.644386 326.948781 481.033211 332.398554 488.729162 337.406280 496.824004 341.731471 505.450592 344.847050 514.505467 346.273079 523.641791 345.634230 531.363205 343.007147 538.344863 338.775789 544.557036 333.469616 550.104748 327.468388 555.042670 320.955462 559.338440 314.002362 562.972779 306.681418 565.886990 299.046109 567.885891 291.124182 568.686858 282.996442 568.329324 274.832261 567.362148 266.713985 566.337311 258.602427 565.557438 250.463763 564.955117 242.309851 564.444580 234.149597 471.059998 245.632004 477.933960 239.912994 485.355957 238.506989 493.459991 238.722000 501.329010 239.512985 501.420013 242.654984 493.565002 241.919983 485.631989 242.110001 478.082001 243.664993 526.028015 238.210999 532.624023 235.848007 539.804016 233.985992 547.359985 234.171005 554.721985 238.779999 547.375977 237.229996 539.919983 236.927017 532.731995 238.679977 526.185974 241.385986 515.885986 246.404999 517.854675 257.799101 519.362448 269.157810 521.301453 278.802002 501.697998 280.035004 510.853386 284.392783 520.824410 285.971955 529.274373 283.621750 536.371826 278.343109 476.043365 249.347351 481.205421 245.721604 487.219472 243.910831 493.929766 244.744156 498.989990 249.270996 493.507200 250.833897 487.843107 251.410172 481.876172 250.783584 528.823975 246.457993 533.831647 241.023355 541.029509 239.365086 545.516313 240.330809 549.558044 242.554535 545.888268 245.029787 541.799786 246.697932 535.314083 247.197977 491.536499 296.518005 504.988051 293.530367 518.661577 293.974240 521.153924 293.457321 525.046744 292.283978 534.985857 291.943620 544.928772 291.050842 537.916805 300.178389 530.006290 308.422948 518.954456 311.332508 507.488208 311.322321 497.254748 306.407774 492.901978 297.799988 507.390162 297.651260 521.818632 297.157243 532.476975 294.174984 543.362244 292.184601 533.178825 302.624248 518.991571 306.016405 504.805119 305.517077 489.532515 247.446626 541.007362 242.970552</landmarks>
  </object>
</annotation>
