<annotation>
  <folder>train</folder>
  <filename>043_0336.jpg</filename>
  <path>E:/DB_FaceLandmark/300VW_frame/train\043_0336.jpg</path>
  <size>
    <height>720</height>
    <width>1280</width>
    <depth>3</depth>
  </size>
  <object>
    <bbox>
      <xmin>584</xmin>
      <ymin>174</ymin>
      <xmax>814</xmax>
      <ymax>410</ymax>
    </bbox>
    <landmarks>590.703 186.478 586.317 218.898 584.143 252.963 585.06 287.184 591.249 321.96 602.374 354.829 618.491 382.411 640.287 403.129 669.797 410.223 700.783 408.075 729.779 393.073 756.824 373.051 778.203 347.906 794.596 319.408 804.251 288.013 809.82 256.414 814.993 224.285 611.364 185.286 624.031 175.39 642.337 174.027 661.399 179.301 677.851 188.459 706.427 191.127 725.988 186.955 746.965 188.289 765.473 195.002 777.804 206.644 689.628 204.67 685.475 226.662 681.292 248.883 677.264 271.65 654.069 278.492 663.575 286.49 675.717 292.7 690.483 289.206 703.163 284.408 625.535 201.291 636.642 197.85 648.082 198.94 658.634 204.666 646.559 206.042 634.987 205.347 718.996 211.206 730.864 207.614 742.225 209.312 751.743 214.813 740.915 216.023 729.831 214.577 635.922 317.647 649.639 311.192 663.655 311.089 673.679 314.756 686.443 313.517 701.883 317.166 717.637 326.637 699.582 331.23 683.709 332.134 671.103 331.616 660.399 329.309 648.181 325.392 641.625 317.347 662.625 318.172 673.154 320.652 685.704 320.413 710.866 325.074 685.196 321.182 672.767 321.059 662.314 318.795</landmarks>
  </object>
</annotation>
