<annotation>
  <folder>11--Meeting</folder>
  <filename>11_Meeting_Meeting_11_Meeting_Meeting_11_114.jpg</filename>
  <path>WFLW_images\11--Meeting\11_Meeting_Meeting_11_Meeting_Meeting_11_114.jpg</path>
  <size>
    <height>1327</height>
    <width>1024</width>
    <depth>3</depth>
  </size>
  <object>
    <bbox>
      <xmin>29</xmin>
      <ymin>251</ymin>
      <xmax>358</xmax>
      <ymax>624</ymax>
    </bbox>
    <landmarks>24.743015 333.159058 24.165358 376.617315 26.606258 419.994735 34.689110 462.651744 50.988390 502.856882 72.572484 540.577650 95.196362 577.680829 123.462269 610.501631 163.165962 626.160097 214.857335 618.319283 264.533479 601.491178 311.650964 578.452262 354.612057 548.448919 389.023262 509.055552 411.515735 461.794288 422.184856 410.504631 425.576996 358.141998 35.392395 347.523010 55.863499 321.765961 77.998901 323.288971 103.500999 316.927002 127.035995 318.694000 185.193985 316.101990 214.221985 315.260010 245.011993 322.471008 275.188965 322.729004 309.777008 345.406006 158.451996 357.984985 152.364896 387.715682 148.330017 417.771010 144.624387 447.846531 124.676003 462.664001 139.721515 466.578856 155.266922 466.927134 172.747565 467.120133 190.156570 468.792938 62.665199 358.100006 76.662109 350.828653 114.883660 344.003744 133.026398 359.030426 112.165992 358.902478 76.903567 360.788864 209.138000 362.337006 225.660345 351.073319 266.350347 353.645163 286.014160 363.292328 265.839791 367.911757 227.172310 364.104226</landmarks>
  </object>
</annotation>
