<annotation>
  <folder>2--Demonstration</folder>
  <filename>2_Demonstration_Political_Rally_2_128.jpg</filename>
  <path>WFLW_images\2--Demonstration\2_Demonstration_Political_Rally_2_128.jpg</path>
  <size>
    <height>1544</height>
    <width>1024</width>
    <depth>3</depth>
  </size>
  <object>
    <bbox>
      <xmin>693</xmin>
      <ymin>108</ymin>
      <xmax>818</xmax>
      <ymax>249</ymax>
    </bbox>
    <landmarks>691.127014 171.944000 693.642843 188.070119 697.455279 203.931066 703.668936 218.996680 713.366931 232.046304 726.637289 241.444743 741.938277 247.018245 758.084963 249.224679 774.367233 248.439989 788.333847 245.204463 801.080562 238.715806 810.394148 227.950412 815.069581 214.422749 817.120660 200.219232 818.172975 185.900304 818.143652 171.548260 816.226074 157.330109 706.874023 148.466995 718.132996 138.837006 727.979980 137.072998 738.130981 136.529999 749.059021 136.199020 766.760986 134.821014 776.448975 133.414001 787.773010 132.570984 798.620972 134.510010 808.721008 141.257019 761.767029 151.710999 762.829766 160.514149 763.898902 169.307705 764.948059 178.037186 748.999023 188.401993 757.493705 188.713380 765.814666 186.908416 772.818989 187.302975 779.482849 185.280045 726.452026 157.440002 729.806975 153.472541 741.576712 151.105716 747.428101 155.139297 742.533950 159.159722 731.260455 159.580604 777.283020 153.339996 781.826554 147.973403 793.659774 148.840790 797.968445 151.698303 794.916263 154.835640 783.805494 156.906081</landmarks>
  </object>
</annotation>
