<annotation>
  <folder>45--Balloonist</folder>
  <filename>45_Balloonist_Balloonist_45_1030.jpg</filename>
  <path>WFLW_images\45--Balloonist\45_Balloonist_Balloonist_45_1030.jpg</path>
  <size>
    <height>785</height>
    <width>1024</width>
    <depth>3</depth>
  </size>
  <object>
    <bbox>
      <xmin>444</xmin>
      <ymin>232</ymin>
      <xmax>532</xmax>
      <ymax>356</ymax>
    </bbox>
    <landmarks>446.196106 268.780579 446.248736 281.236443 443.954223 293.523604 444.439307 305.949176 447.434705 318.085146 451.437881 329.916967 457.893484 340.574148 467.521460 348.407546 479.545491 351.509285 492.535558 350.162875 504.461409 344.830701 514.439536 336.368950 522.366439 325.943782 528.303394 314.264857 532.420429 301.820445 535.253450 289.016407 537.448975 276.084991 446.250000 267.872009 453.076996 263.802002 460.269012 266.211029 466.795990 269.605011 473.392029 272.472015 483.911987 273.147003 491.528992 271.856995 499.718994 272.009003 508.390991 272.893005 516.044006 279.348999 478.207001 278.460999 476.627782 287.648341 474.760520 296.756639 474.807453 305.552795 464.582001 304.755005 470.418610 308.218476 476.941195 309.479175 482.139434 306.971529 487.435883 304.640076 452.518066 274.459351 456.611539 271.940348 465.910453 273.097232 468.933990 276.917999 464.597318 278.174697 455.909097 277.259138 490.061005 281.559998 494.225246 278.056308 505.236522 278.589877 509.863007 282.370056 504.333687 284.575815 494.144098 283.326692</landmarks>
  </object>
</annotation>
