<annotation>
  <folder>28--Sports_Fan</folder>
  <filename>28_Sports_Fan_Sports_Fan_28_159.jpg</filename>
  <path>WFLW_images\28--Sports_Fan\28_Sports_Fan_Sports_Fan_28_159.jpg</path>
  <size>
    <height>576</height>
    <width>1024</width>
    <depth>3</depth>
  </size>
  <object>
    <bbox>
      <xmin>500</xmin>
      <ymin>138</ymin>
      <xmax>754</xmax>
      <ymax>450</ymax>
    </bbox>
    <landmarks>492.497986 230.355408 493.978005 265.849252 497.100350 301.230085 503.630575 336.126270 515.506172 369.553974 534.001388 399.793778 559.073702 424.846031 589.356812 443.215621 623.994862 449.839582 659.582652 442.527776 691.548482 424.978596 720.281218 402.488282 742.425279 373.633852 753.183572 338.937121 757.471086 302.665040 764.099704 266.742106 766.585022 230.309998 500.445984 198.370987 522.406006 182.182983 544.893982 178.292023 566.684998 182.098022 586.179993 189.677002 635.187012 190.887985 659.323914 183.823990 683.736023 181.869003 705.768982 185.855988 723.276978 202.138992 613.685974 229.434006 613.049851 250.389991 611.944576 271.140012 612.429443 289.202087 588.085022 309.666992 600.336525 309.886335 612.041993 313.811233 625.198133 308.728701 639.347717 307.501984 534.478027 230.968994 543.323434 225.150821 569.884411 225.517024 584.085388 234.950012 568.374037 237.964478 543.005609 236.208214 648.806030 231.957993 660.100416 223.587018 687.136144 224.469380 698.838013 231.907440 687.199224 236.112637 661.435678 237.010607</landmarks>
  </object>
</annotation>
