<annotation>
  <folder>16--Award_Ceremony</folder>
  <filename>16_Award_Ceremony_Awards_Ceremony_16_445.jpg</filename>
  <path>WFLW_images\16--Award_Ceremony\16_Award_Ceremony_Awards_Ceremony_16_445.jpg</path>
  <size>
    <height>1543</height>
    <width>1024</width>
    <depth>3</depth>
  </size>
  <object>
    <bbox>
      <xmin>145</xmin>
      <ymin>274</ymin>
      <xmax>253</xmax>
      <ymax>416</ymax>
    </bbox>
    <landmarks>140.115005 344.427002 143.566789 361.532979 146.034705 378.807891 152.579151 394.764124 165.962103 405.816914 181.689473 413.342783 198.174257 419.056972 214.936974 423.912134 232.020833 424.043905 239.938614 415.569882 243.033821 403.883257 246.349402 392.355132 249.255277 380.638739 252.778163 369.073128 252.782882 356.971527 251.391969 344.929578 249.746506 332.920502 196.533020 330.221985 203.994019 326.684998 211.882996 324.871033 219.675018 324.580017 226.199020 326.689026 232.763016 326.444000 236.660995 325.107025 240.591019 324.706024 244.139999 324.546997 247.889999 325.792999 232.013000 338.028992 236.487442 348.164035 240.212879 358.585513 243.716418 369.059701 221.406998 371.023987 229.997203 373.070246 237.465653 377.497204 240.340498 377.259423 242.948975 375.970032 202.336929 340.697144 204.530480 338.533130 213.482964 335.776463 219.145996 338.752991 213.225889 341.615768 204.487264 341.277368 234.876999 338.487000 237.947270 335.466923 245.669882 334.710549 248.114700 337.452515 245.315081 338.860935 238.492278 339.818095</landmarks>
  </object>
</annotation>
