<annotation>
  <folder>35--Basketball</folder>
  <filename>35_Basketball_playingbasketball_35_782.jpg</filename>
  <path>WFLW_images\35--Basketball\35_Basketball_playingbasketball_35_782.jpg</path>
  <size>
    <height>1186</height>
    <width>1024</width>
    <depth>3</depth>
  </size>
  <object>
    <bbox>
      <xmin>507</xmin>
      <ymin>322</ymin>
      <xmax>614</xmax>
      <ymax>468</ymax>
    </bbox>
    <landmarks>509.627991 387.230988 510.187980 399.386045 510.984769 411.527493 512.500558 423.595318 515.897403 435.254260 522.255901 445.577522 531.133386 453.855078 541.684393 459.863145 553.361421 463.159104 565.982621 463.077808 578.185401 459.793429 589.388075 453.944359 598.585195 445.317804 604.794883 434.317300 608.903096 422.348012 611.672774 409.993650 613.760132 397.502625 521.465088 371.409027 527.382080 363.760040 533.598083 361.594025 540.808044 360.521027 547.739075 361.461060 574.327087 363.023041 582.925049 363.021027 591.044067 364.814056 598.445068 369.340057 603.617065 378.989014 561.031982 377.427002 560.601998 383.550619 560.004171 389.658489 559.490887 395.766707 547.380005 406.842987 553.424740 408.307603 559.353739 409.904435 563.820529 408.973654 568.322876 408.228027 529.163025 379.316010 532.965243 375.222551 544.283377 374.757450 548.183228 379.718781 543.136253 381.560972 533.402837 380.754338 573.281982 381.902008 576.698726 376.133700 588.707669 378.799303 592.086426 383.788788 587.829408 384.261583 578.343209 383.396144</landmarks>
  </object>
</annotation>
