<annotation>
  <folder>27--Spa</folder>
  <filename>27_Spa_Spa_27_46.jpg</filename>
  <path>WFLW_images\27--Spa\27_Spa_Spa_27_46.jpg</path>
  <size>
    <height>770</height>
    <width>1024</width>
    <depth>3</depth>
  </size>
  <object>
    <bbox>
      <xmin>340</xmin>
      <ymin>132</ymin>
      <xmax>708</xmax>
      <ymax>608</ymax>
    </bbox>
    <landmarks>327.873230 288.218018 332.321512 338.874922 342.558038 388.724516 347.773649 439.368632 364.231237 487.413990 393.031163 529.287502 428.269841 566.044111 469.836239 595.163611 519.164474 606.041869 566.046115 595.616029 606.277020 569.146546 639.578284 534.113850 669.892580 496.474764 689.702522 452.603124 697.007932 404.876264 701.950974 356.789511 709.398987 309.010010 368.549011 251.126999 400.791016 239.273987 433.522003 234.199005 465.528992 240.102005 495.664001 245.106995 560.447021 246.128998 590.742981 241.848007 620.416016 241.714020 651.481995 246.906006 678.224976 264.722992 527.432007 281.389008 525.382083 318.050504 523.360903 354.712889 520.649689 391.315528 477.315002 400.787994 498.383524 411.457497 520.617725 418.986002 544.496541 412.814981 567.829651 404.209137 404.040985 284.894012 412.326273 276.272394 453.468239 271.931502 480.160522 289.126892 451.768901 294.047887 413.399430 289.285589 573.163025 296.587006 591.330411 282.179522 630.571003 283.193026 640.683044 297.881073 628.292957 299.745567 594.372324 299.560677</landmarks>
  </object>
</annotation>
