<annotation>
  <folder>2--Demonstration</folder>
  <filename>2_Demonstration_Political_Rally_2_803.jpg</filename>
  <path>WFLW_images\2--Demonstration\2_Demonstration_Political_Rally_2_803.jpg</path>
  <size>
    <height>688</height>
    <width>1024</width>
    <depth>3</depth>
  </size>
  <object>
    <bbox>
      <xmin>0</xmin>
      <ymin>6</ymin>
      <xmax>87</xmax>
      <ymax>167</ymax>
    </bbox>
    <landmarks>-48.431999 80.166000 -42.091117 98.924673 -34.548136 117.225523 -24.464737 134.231199 -10.403181 148.056325 6.992247 157.431483 25.772969 163.656854 45.240269 167.191256 64.966102 166.632814 76.911452 161.830239 84.806424 151.689953 88.269146 139.229590 88.778635 126.274169 87.357563 113.376898 84.692874 100.673361 81.225967 88.171971 78.788200 75.475815 -14.034299 65.230202 -6.127881 55.289398 4.030871 53.382301 14.116300 54.187901 22.826300 56.207005 52.371601 57.037498 59.679100 56.793800 66.385399 57.169498 72.207397 59.151505 77.271690 70.196602 43.299702 71.454498 48.334193 79.874645 53.355711 88.302513 58.471564 96.672986 35.015301 110.639000 42.916579 108.325517 51.066386 107.253213 55.966525 107.946115 60.687134 109.471939 -6.043971 73.348099 0.690207 70.182504 15.304669 71.626728 21.044399 76.578903 15.593515 76.931362 1.787166 76.658421 52.176899 77.565002 58.233916 73.023728 70.301363 74.371265 73.452057 78.130966 70.157494 79.560101 59.521402 77.750115</landmarks>
  </object>
</annotation>
