<annotation>
  <folder>4--Dancing</folder>
  <filename>4_Dancing_Dancing_4_1029.jpg</filename>
  <path>WFLW_images\4--Dancing\4_Dancing_Dancing_4_1029.jpg</path>
  <size>
    <height>1075</height>
    <width>1024</width>
    <depth>3</depth>
  </size>
  <object>
    <bbox>
      <xmin>560</xmin>
      <ymin>61</ymin>
      <xmax>646</xmax>
      <ymax>212</ymax>
    </bbox>
    <landmarks>564.092041 137.726242 566.806262 149.001923 565.979575 160.966264 573.602255 169.760911 581.665657 178.575365 585.408611 189.886548 593.870701 198.213793 599.639123 208.700456 609.653015 214.598850 622.849089 212.092458 632.736880 202.682418 639.894087 191.046197 643.886237 177.954090 646.343506 164.469301 648.504910 150.935880 648.591550 137.239608 648.862000 123.538002 561.380981 126.053001 563.161987 122.346992 565.332031 124.621002 567.635010 126.601997 569.776978 128.699982 579.786011 123.474007 585.890991 120.845009 592.739014 120.433990 599.620972 122.062996 605.911987 126.707016 576.414001 136.492996 575.017632 145.122194 573.942232 153.725942 574.573181 160.249893 579.380005 166.828995 579.927201 166.406789 580.486837 166.001307 584.376433 164.482415 588.531921 163.804001 563.865051 137.131027 562.969470 134.312130 569.859342 133.685933 574.190979 136.326996 571.324029 138.525906 565.373760 139.321022 587.940979 134.367996 587.483158 131.734964 594.691760 129.097944 600.732422 130.566437 597.127761 133.649128 590.188250 136.025202</landmarks>
  </object>
</annotation>
