<annotation>
  <folder>2--Demonstration</folder>
  <filename>2_Demonstration_Protesters_2_282.jpg</filename>
  <path>WFLW_images\2--Demonstration\2_Demonstration_Protesters_2_282.jpg</path>
  <size>
    <height>576</height>
    <width>1024</width>
    <depth>3</depth>
  </size>
  <object>
    <bbox>
      <xmin>45</xmin>
      <ymin>275</ymin>
      <xmax>114</xmax>
      <ymax>328</ymax>
    </bbox>
    <landmarks>42.989498 281.696991 43.592815 289.508307 45.719578 297.035535 48.905601 304.195915 52.652374 311.077897 57.179368 317.469788 62.683721 323.033877 69.366981 327.073035 76.995073 328.673798 85.868841 326.952829 94.038415 322.988460 101.023199 317.240982 105.169087 309.211674 106.977793 300.314855 107.641821 291.250321 107.563672 282.160874 107.014641 273.085938 44.319996 278.019012 47.937695 275.338013 51.688503 275.229004 55.757805 275.161987 59.612202 275.276001 72.440697 274.743042 76.723900 274.514008 81.136398 273.932007 85.558197 273.434021 90.280998 275.604004 66.081902 284.031006 66.307433 290.491901 66.539946 296.942712 64.240521 302.949052 62.452000 299.962006 65.333368 300.043219 68.213687 299.952885 71.109772 299.607161 73.980270 299.087006 48.198002 283.510986 51.392465 281.421420 57.001102 282.012692 58.658241 283.137695 56.662434 284.417521 51.165040 284.915192 73.868896 283.631989 77.789758 281.236419 83.867948 282.230060 85.292778 283.211517 84.137370 283.939161 78.297863 285.296459</landmarks>
  </object>
</annotation>
