<annotation>
  <folder>56--Voter</folder>
  <filename>56_Voter_peoplevoting_56_265.jpg</filename>
  <path>WFLW_images\56--Voter\56_Voter_peoplevoting_56_265.jpg</path>
  <size>
    <height>687</height>
    <width>1024</width>
    <depth>3</depth>
  </size>
  <object>
    <bbox>
      <xmin>193</xmin>
      <ymin>154</ymin>
      <xmax>369</xmax>
      <ymax>362</ymax>
    </bbox>
    <landmarks>193.431473 224.804199 191.580485 247.613638 191.825007 270.481142 195.509138 293.045925 202.660666 314.760424 213.729840 334.739886 229.352241 351.364933 249.182929 362.596304 271.576274 366.688581 293.719096 363.063814 314.144022 353.703605 331.913282 339.935422 346.368912 322.718244 356.780671 302.797675 363.131425 281.213219 366.844275 259.004892 369.312012 236.617996 205.698013 216.869995 218.031998 202.479996 230.119003 201.219009 241.680008 202.837997 253.301010 205.921005 286.563995 204.567993 301.089996 202.251007 316.036987 201.245010 330.497040 203.539001 343.630005 221.126007 267.584015 232.901993 265.226261 247.854898 264.796673 262.667020 263.598785 274.778870 246.994003 283.721985 256.287777 284.758140 265.474817 286.453418 274.554834 284.714232 283.771790 283.983002 218.207367 230.710709 225.250448 226.574756 244.095901 227.095811 251.397003 235.533997 242.621442 236.186685 225.387451 235.502172 291.230011 235.604996 300.419412 227.624537 320.620290 228.166764 327.808990 233.099594 320.406708 237.823361 301.394909 237.356351</landmarks>
  </object>
</annotation>
