<annotation>
  <folder>train</folder>
  <filename>018_1075.jpg</filename>
  <path>300VW_frame\train\018_1075.jpg</path>
  <size>
    <height>720</height>
    <width>1280</width>
    <depth>3</depth>
  </size>
  <object>
    <bbox>
      <xmin>622</xmin>
      <ymin>136</ymin>
      <xmax>773</xmax>
      <ymax>302</ymax>
    </bbox>
    <landmarks>626.28 171.971 623.041 188.068 622.631 205.405 625.233 223.642 628.172 242.495 632.92 262.352 639.907 280.305 649.963 295.728 666.322 302.316 687.842 300.902 711.213 292.349 731.935 279.339 748.451 262.914 759.938 243.127 766.762 220.885 770.921 198.162 773.895 174.742 625.941 143.133 629.688 137.856 635.908 136.303 643.288 137.736 649.771 142.391 678.823 142.103 692.548 137.335 707.794 137.305 721.992 143.22 733.756 153.107 662.101 165.111 658.382 176.303 654.238 187.398 650.171 198.76 645.417 210.501 649.793 213.999 655.694 216.585 663.718 215.277 672.188 214.073 628.566 167.407 635.243 165.219 642.876 165.433 650.384 167.974 642.904 169.206 635.413 169.2 688.798 170.412 696.625 168.939 705.628 170.464 715.056 173.503 705.608 174.174 696.698 173.181</landmarks>
  </object>
</annotation>
