<annotation>
  <folder>train</folder>
  <filename>037_0100.jpg</filename>
  <path>300VW_frame\train\037_0100.jpg</path>
  <size>
    <height>360</height>
    <width>640</width>
    <depth>3</depth>
  </size>
  <object>
    <bbox>
      <xmin>313</xmin>
      <ymin>66</ymin>
      <xmax>506</xmax>
      <ymax>264</ymax>
    </bbox>
    <landmarks>313.228 120.48 318.141 144.498 324.163 167.829 330.99 191.451 340.882 215.147 356.13 235.913 377.174 251.828 401.851 263.402 429.422 264.313 455.84 256.922 476.852 240.003 493.533 218.702 503.577 194.029 506.92 167.629 506.48 141.271 504.392 115.571 501.132 90.211 328.504 104.428 336.255 90.534 351.131 82.811 368.294 81.634 385.265 84.131 416.436 78.343 431.839 70.454 448.485 66.236 465.287 68.563 477.687 78.382 403.335 98.989 405.783 114.59 408.267 130.052 410.972 146.442 396.234 162.793 405.069 164.988 414.731 165.894 423.698 161.456 431.762 156.574 350.362 110.809 359.661 104.566 370.911 102.749 381.27 107.068 371.666 111.237 360.597 112.806 429.017 98.491 438.011 91.104 449.011 89.493 458.826 92.772 450.534 97.668 439.718 99.277</landmarks>
  </object>
</annotation>
